edafos/__init__.py
edafos/stresses.py
edafos-0.0.1.dev0.dist-info/LICENSE
edafos-0.0.1.dev0.dist-info/METADATA
edafos-0.0.1.dev0.dist-info/WHEEL
edafos-0.0.1.dev0.dist-info/top_level.txt
edafos-0.0.1.dev0.dist-info/RECORD
