Metadata-Version: 2.1
Name: edafos
Version: 0.0.1.dev0
Summary: A Suite of Soil Mechanics Algorithms
Home-page: https://github.com/nickmachairas/edafos
Author: Nick Machairas
Author-email: nick@machairas.com
License: UNKNOWN
Platform: UNKNOWN
Classifier: Programming Language :: Python :: 3
Classifier: License :: OSI Approved :: MIT License
Classifier: Operating System :: OS Independent
Requires-Python: >=3.6
Requires-Dist: numpy (==1.18.1)
Requires-Dist: Pint (==0.10.1)
